README.md
setup.py
RudolfTools.egg-info/PKG-INFO
RudolfTools.egg-info/SOURCES.txt
RudolfTools.egg-info/dependency_links.txt
RudolfTools.egg-info/top_level.txt
my_tools/__init__.py
my_tools/hello.py