Metadata-Version: 2.1
Name: RudolfTools
Version: 0.0.1
Summary: My own little python-tools repo
Home-page: UNKNOWN
Author: Rudolf07688 (Rudolf Lüttich)
Author-email: <rudolfluttich@gmail.com>
License: Creative Commons Attribution-Noncommercial-Share Alike license
Keywords: python,personal,utils
Platform: UNKNOWN
Classifier: Development Status :: 1 - Planning
Classifier: Intended Audience :: Developers
Classifier: Programming Language :: Python :: 3
Classifier: Operating System :: Unix
Classifier: Operating System :: MacOS :: MacOS X
